langgraph/checkpoint/opensearch/__init__.py
langgraph/checkpoint/opensearch/jsonplus_ext_opensearch.py
langgraph/checkpoint/opensearch/saver.py
langgraph/checkpoint/opensearch/utils.py
langgraph/store/opensearch/__init__.py
langgraph/store/opensearch/base.py
langgraph_opensearch-0.1.5.dist-info/METADATA
langgraph_opensearch-0.1.5.dist-info/WHEEL
langgraph_opensearch-0.1.5.dist-info/licenses/LICENSE
langgraph_opensearch-0.1.5.dist-info/RECORD
