Metadata-Version: 2.4
Name: langgraph-opensearch
Version: 0.1.5
Summary: Library with an OpenSearch implementation of LangGraph checkpoint saver.
Author-email: Samriddha Chatterjee <samriddhac.official@gmail.com>
License: MIT
License-File: LICENSE
Requires-Python: <4,>=3.12
Requires-Dist: langgraph-checkpoint<3.0.0,>=2.0.23
Requires-Dist: opensearch-py<4.0.0,>=3.0.0
